Workbook

Sheet Annual Budget Overview
A1: 📊 Annual Budget Overview 2026
A2: Category | B2: Budget | C2: Committed | D2: Actual | E2: Remaing | F2: Q1 2026 | G2: Q2 2026 | H2: Q3 2026 | I2: Q4 2026
A3: Content & Thought Leadership | B3: 25000 | C3: =SUMIFS('Spend Tracker'!H:H,'Spend Tracker'!C:C,$A3,'Spend Tracker'!F:F,"Committed") -> 0 | D3: =SUMIFS('Spend Tracker'!H:H,'Spend Tracker'!C:C,$A3,'Spend Tracker'!F:F,"Spent") -> 0 | E3: =B3-C3-D3 -> 25000 | F3: =SUMIFS('Spend Tracker'!H:H,'Spend Tracker'!C:C,$A3,'Spend Tracker'!F:F,"Spent",'Spend Tracker'!B:B,F$2) -> 0 | G3: =SUMIFS('Spend Tracker'!H:H,'Spend Tracker'!C:C,$A3,'Spend Tracker'!F:F,"Spent",'Spend Tracker'!B:B,G$2) -> 0 | H3: =SUMIFS('Spend Tracker'!H:H,'Spend Tracker'!C:C,$A3,'Spend Tracker'!F:F,"Spent",'Spend Tracker'!B:B,H$2) -> 0 | I3: =SUMIFS('Spend Tracker'!H:H,'Spend Tracker'!C:C,$A3,'Spend Tracker'!F:F,"Spent",'Spend Tracker'!B:B,I$2) -> 0
A4: Paid Media | B4: 57000 | C4: =SUMIFS('Spend Tracker'!H:H,'Spend Tracker'!C:C,$A4,'Spend Tracker'!F:F,"Committed") -> 0 | D4: =SUMIFS('Spend Tracker'!H:H,'Spend Tracker'!C:C,$A4,'Spend Tracker'!F:F,"Spent") -> 1690.99 | E4: =B4-C4-D4 -> 55309.01 | F4: =SUMIFS('Spend Tracker'!H:H,'Spend Tracker'!C:C,$A4,'Spend Tracker'!F:F,"Spent",'Spend Tracker'!B:B,F$2) -> 0 | G4: =SUMIFS('Spend Tracker'!H:H,'Spend Tracker'!C:C,$A4,'Spend Tracker'!F:F,"Spent",'Spend Tracker'!B:B,G$2) -> 1690.99 | H4: =SUMIFS('Spend Tracker'!H:H,'Spend Tracker'!C:C,$A4,'Spend Tracker'!F:F,"Spent",'Spend Tracker'!B:B,H$2) -> 0 | I4: =SUMIFS('Spend Tracker'!H:H,'Spend Tracker'!C:C,$A4,'Spend Tracker'!F:F,"Spent",'Spend Tracker'!B:B,I$2) -> 0
A5: PR | B5: 25000 | C5: =SUMIFS('Spend Tracker'!H:H,'Spend Tracker'!C:C,$A5,'Spend Tracker'!F:F,"Committed") -> 0 | D5: =SUMIFS('Spend Tracker'!H:H,'Spend Tracker'!C:C,$A5,'Spend Tracker'!F:F,"Spent") -> 650 | E5: =B5-C5-D5 -> 24350 | F5: =SUMIFS('Spend Tracker'!H:H,'Spend Tracker'!C:C,$A5,'Spend Tracker'!F:F,"Spent",'Spend Tracker'!B:B,F$2) -> 650 | G5: =SUMIFS('Spend Tracker'!H:H,'Spend Tracker'!C:C,$A5,'Spend Tracker'!F:F,"Spent",'Spend Tracker'!B:B,G$2) -> 0 | H5: =SUMIFS('Spend Tracker'!H:H,'Spend Tracker'!C:C,$A5,'Spend Tracker'!F:F,"Spent",'Spend Tracker'!B:B,H$2) -> 0 | I5: =SUMIFS('Spend Tracker'!H:H,'Spend Tracker'!C:C,$A5,'Spend Tracker'!F:F,"Spent",'Spend Tracker'!B:B,I$2) -> 0
A6: Tools & Martech | B6: 20000 | C6: =SUMIFS('Spend Tracker'!H:H,'Spend Tracker'!C:C,$A6,'Spend Tracker'!F:F,"Committed") -> 0 | D6: =SUMIFS('Spend Tracker'!H:H,'Spend Tracker'!C:C,$A6,'Spend Tracker'!F:F,"Spent") -> 5489.72 | E6: =B6-C6-D6 -> 14510.28 | F6: =SUMIFS('Spend Tracker'!H:H,'Spend Tracker'!C:C,$A6,'Spend Tracker'!F:F,"Spent",'Spend Tracker'!B:B,F$2) -> 4010.57 | G6: =SUMIFS('Spend Tracker'!H:H,'Spend Tracker'!C:C,$A6,'Spend Tracker'!F:F,"Spent",'Spend Tracker'!B:B,G$2) -> 1479.15 | H6: =SUMIFS('Spend Tracker'!H:H,'Spend Tracker'!C:C,$A6,'Spend Tracker'!F:F,"Spent",'Spend Tracker'!B:B,H$2) -> 0 | I6: =SUMIFS('Spend Tracker'!H:H,'Spend Tracker'!C:C,$A6,'Spend Tracker'!F:F,"Spent",'Spend Tracker'!B:B,I$2) -> 0
A7: Agency / External | B7: 120000 | C7: =SUMIFS('Spend Tracker'!H:H,'Spend Tracker'!C:C,$A7,'Spend Tracker'!F:F,"Committed") -> 0 | D7: =SUMIFS('Spend Tracker'!H:H,'Spend Tracker'!C:C,$A7,'Spend Tracker'!F:F,"Spent") -> 69728.54 | E7: =B7-C7-D7 -> 50271.46 | F7: =SUMIFS('Spend Tracker'!H:H,'Spend Tracker'!C:C,$A7,'Spend Tracker'!F:F,"Spent",'Spend Tracker'!B:B,F$2) -> 38797.37 | G7: =SUMIFS('Spend Tracker'!H:H,'Spend Tracker'!C:C,$A7,'Spend Tracker'!F:F,"Spent",'Spend Tracker'!B:B,G$2) -> 30931.17 | H7: =SUMIFS('Spend Tracker'!H:H,'Spend Tracker'!C:C,$A7,'Spend Tracker'!F:F,"Spent",'Spend Tracker'!B:B,H$2) -> 0 | I7: =SUMIFS('Spend Tracker'!H:H,'Spend Tracker'!C:C,$A7,'Spend Tracker'!F:F,"Spent",'Spend Tracker'!B:B,I$2) -> 0
A8: Event (Owned) | B8: 50000 | C8: =SUMIFS('Spend Tracker'!H:H,'Spend Tracker'!C:C,$A8,'Spend Tracker'!F:F,"Committed") -> 0 | D8: =SUMIFS('Spend Tracker'!H:H,'Spend Tracker'!C:C,$A8,'Spend Tracker'!F:F,"Spent") -> 1902.74 | E8: =B8-C8-D8 -> 48097.26 | F8: =SUMIFS('Spend Tracker'!H:H,'Spend Tracker'!C:C,$A8,'Spend Tracker'!F:F,"Spent",'Spend Tracker'!B:B,F$2) -> 320.97 | G8: =SUMIFS('Spend Tracker'!H:H,'Spend Tracker'!C:C,$A8,'Spend Tracker'!F:F,"Spent",'Spend Tracker'!B:B,G$2) -> 1581.77 | H8: =SUMIFS('Spend Tracker'!H:H,'Spend Tracker'!C:C,$A8,'Spend Tracker'!F:F,"Spent",'Spend Tracker'!B:B,H$2) -> 0 | I8: =SUMIFS('Spend Tracker'!H:H,'Spend Tracker'!C:C,$A8,'Spend Tracker'!F:F,"Spent",'Spend Tracker'!B:B,I$2) -> 0
A9: Event (Earned) | B9: 50000 | C9: =SUMIFS('Spend Tracker'!H:H,'Spend Tracker'!C:C,$A9,'Spend Tracker'!F:F,"Committed") -> 0 | D9: =SUMIFS('Spend Tracker'!H:H,'Spend Tracker'!C:C,$A9,'Spend Tracker'!F:F,"Spent") -> 12984.03 | E9: =B9-C9-D9 -> 37015.97 | F9: =SUMIFS('Spend Tracker'!H:H,'Spend Tracker'!C:C,$A9,'Spend Tracker'!F:F,"Spent",'Spend Tracker'!B:B,F$2) -> 6650 | G9: =SUMIFS('Spend Tracker'!H:H,'Spend Tracker'!C:C,$A9,'Spend Tracker'!F:F,"Spent",'Spend Tracker'!B:B,G$2) -> 6334.03 | H9: =SUMIFS('Spend Tracker'!H:H,'Spend Tracker'!C:C,$A9,'Spend Tracker'!F:F,"Spent",'Spend Tracker'!B:B,H$2) -> 0 | I9: =SUMIFS('Spend Tracker'!H:H,'Spend Tracker'!C:C,$A9,'Spend Tracker'!F:F,"Spent",'Spend Tracker'!B:B,I$2) -> 0
A10: MDF | B10: 60863.92 | C10: =SUMIFS('Spend Tracker'!H:H,'Spend Tracker'!C:C,$A10,'Spend Tracker'!F:F,"Committed") -> 0 | D10: =SUMIFS('Spend Tracker'!H:H,'Spend Tracker'!C:C,$A10,'Spend Tracker'!F:F,"Spent") -> 574.56 | E10: =B10-C10-D10 -> 60289.36 | F10: =SUMIFS('Spend Tracker'!H:H,'Spend Tracker'!C:C,$A10,'Spend Tracker'!F:F,"Spent",'Spend Tracker'!B:B,F$2) -> 0 | G10: =SUMIFS('Spend Tracker'!H:H,'Spend Tracker'!C:C,$A10,'Spend Tracker'!F:F,"Spent",'Spend Tracker'!B:B,G$2) -> 574.56 | H10: =SUMIFS('Spend Tracker'!H:H,'Spend Tracker'!C:C,$A10,'Spend Tracker'!F:F,"Spent",'Spend Tracker'!B:B,H$2) -> 0 | I10: =SUMIFS('Spend Tracker'!H:H,'Spend Tracker'!C:C,$A10,'Spend Tracker'!F:F,"Spent",'Spend Tracker'!B:B,I$2) -> 0
A11: Translation | B11: 8000 | C11: =SUMIFS('Spend Tracker'!H:H,'Spend Tracker'!C:C,$A11,'Spend Tracker'!F:F,"Committed") -> 0 | D11: =SUMIFS('Spend Tracker'!H:H,'Spend Tracker'!C:C,$A11,'Spend Tracker'!F:F,"Spent") -> 167.19 | E11: =B11-C11-D11 -> 7832.81 | F11: =SUMIFS('Spend Tracker'!H:H,'Spend Tracker'!C:C,$A11,'Spend Tracker'!F:F,"Spent",'Spend Tracker'!B:B,F$2) -> 0 | G11: =SUMIFS('Spend Tracker'!H:H,'Spend Tracker'!C:C,$A11,'Spend Tracker'!F:F,"Spent",'Spend Tracker'!B:B,G$2) -> 167.19 | H11: =SUMIFS('Spend Tracker'!H:H,'Spend Tracker'!C:C,$A11,'Spend Tracker'!F:F,"Spent",'Spend Tracker'!B:B,H$2) -> 0 | I11: =SUMIFS('Spend Tracker'!H:H,'Spend Tracker'!C:C,$A11,'Spend Tracker'!F:F,"Spent",'Spend Tracker'!B:B,I$2) -> 0
A12: Other | B12: 25000 | C12: =SUMIFS('Spend Tracker'!H:H,'Spend Tracker'!C:C,$A12,'Spend Tracker'!F:F,"Committed") -> 0 | D12: =SUMIFS('Spend Tracker'!H:H,'Spend Tracker'!C:C,$A12,'Spend Tracker'!F:F,"Spent") -> 5631.62 | E12: =B12-C12-D12 -> 19368.38 | F12: =SUMIFS('Spend Tracker'!H:H,'Spend Tracker'!C:C,$A12,'Spend Tracker'!F:F,"Spent",'Spend Tracker'!B:B,F$2) -> 2566.53 | G12: =SUMIFS('Spend Tracker'!H:H,'Spend Tracker'!C:C,$A12,'Spend Tracker'!F:F,"Spent",'Spend Tracker'!B:B,G$2) -> 3065.09 | H12: =SUMIFS('Spend Tracker'!H:H,'Spend Tracker'!C:C,$A12,'Spend Tracker'!F:F,"Spent",'Spend Tracker'!B:B,H$2) -> 0 | I12: =SUMIFS('Spend Tracker'!H:H,'Spend Tracker'!C:C,$A12,'Spend Tracker'!F:F,"Spent",'Spend Tracker'!B:B,I$2) -> 0
A13: Totals | B13: =SUM(B3:B12) -> 440863.92 | C13: =SUM(C3:C12) -> 0 | D13: =SUM(D3:D12) -> 98819.39 | E13: =SUM(E3:E12) -> 342044.53 | F13: =SUM(F3:F12) -> 52995.44 | G13: =SUM(G3:G12) -> 45823.95 | H13: =SUM(H3:H12) -> 0 | I13: =SUM(I3:I12) -> 0

Sheet Spend Tracker
A1: 🧾 Spend Tracker
A2: Date | B2: Quarter | C2: Budget Line | D2: Primary Audience | E2: Market | F2: Status | G2: Owner | H2: Cost (€) | I2: Notes
A3: 46054 | B3: ="Q"&ROUNDUP(MONTH(A3)/3,0)&" "&YEAR(A3) -> Q1 2026 | C3: Agency / External | D3: Prospects / Partners / Clients | E3: NL | F3: Spent | G3: Agency | H3: 457.92 | I3: SEO optimisation
A4: 46030 | B4: ="Q"&ROUNDUP(MONTH(A4)/3,0)&" "&YEAR(A4) -> Q1 2026 | C4: Agency / External | D4: Current Clients / Prospects | E4: ALL | F4: Spent | G4: Agency | H4: 2500 | I4: Monthly invoice AI system build out & deployment
A5: 46036 | B5: ="Q"&ROUNDUP(MONTH(A5)/3,0)&" "&YEAR(A5) -> Q1 2026 | C5: Agency / External | D5: Prospects | E5: ALL | F5: Spent | G5: Agency | H5: 576.81 | I5: SoPro
A6: 46036 | B6: ="Q"&ROUNDUP(MONTH(A6)/3,0)&" "&YEAR(A6) -> Q1 2026 | C6: Tools & Martech | D6: Prospects / Partners / Clients | E6: ALL | F6: Spent | G6: Marketing | H6: 79.6 | I6: GoTo Webinar
A7: 46042 | B7: ="Q"&ROUNDUP(MONTH(A7)/3,0)&" "&YEAR(A7) -> Q1 2026 | C7: Other | D7: Internal | E7: NL | F7: Spent | G7: Marketing | H7: 1325.95 | I7: Office signage rebrand
A8: 46052 | B8: ="Q"&ROUNDUP(MONTH(A8)/3,0)&" "&YEAR(A8) -> Q1 2026 | C8: Agency / External | D8: Prospects | E8: ALL | F8: Spent | G8: Agency | H8: 2164.21 | I8: SoPro
A9: 46052 | B9: ="Q"&ROUNDUP(MONTH(A9)/3,0)&" "&YEAR(A9) -> Q1 2026 | C9: Agency / External | D9: Prospects / Partners / Clients | E9: ALL | F9: Spent | G9: Agency | H9: 20632.7 | I9: Retainer Fluro
A10: 46053 | B10: ="Q"&ROUNDUP(MONTH(A10)/3,0)&" "&YEAR(A10) -> Q1 2026 | C10: Other | D10: Internal | E10: ALL | F10: Spent | G10: Marketing | H10: 90 | I10: Balloon for Microsoft fiming
A11: 46053 | B11: ="Q"&ROUNDUP(MONTH(A11)/3,0)&" "&YEAR(A11) -> Q1 2026 | C11: Tools & Martech | D11: Internal | E11: ALL | F11: Spent | G11: Marketing | H11: 52.43 | I11: ChatGPT license
A12: 46053 | B12: ="Q"&ROUNDUP(MONTH(A12)/3,0)&" "&YEAR(A12) -> Q1 2026 | C12: Agency / External | D12: Internal | E12: ALL | F12: Spent | G12: Marketing | H12: 6633.38 | I12: Marketing executive support
A13: 46053 | B13: ="Q"&ROUNDUP(MONTH(A13)/3,0)&" "&YEAR(A13) -> Q1 2026 | C13: Tools & Martech | D13: Prospects | E13: ALL | F13: Spent | G13: SMA | H13: 733.85 | I13: Outreach license
A14: 46054 | B14: ="Q"&ROUNDUP(MONTH(A14)/3,0)&" "&YEAR(A14) -> Q1 2026 | C14: Agency / External | D14: Internal | E14: ALL | F14: Spent | G14: Marketing | H14: -18015.07 | I14: Correction rebrand related costs
... A90: 46154 | B90: ="Q"&ROUNDUP(MONTH(A90)/3,0)&" "&YEAR(A90) -> Q2 2026 | C90: Event (Earned) | D90: Prospects / Partners / Clients | E90: BELUX | F90: Spent | G90: SMA | H90: 119.04 | I90: Parking Cybersec

Sheet TEST IGNORE
D2: Brand & Awareness | G2: =SUMIF($D$14:$D$57,$D2,$G$14:$G$57) -> 10
D3: Demand Generation | G3: =SUMIF($D$14:$D$57,$D3,$G$14:$G$57) -> 32
D4: Content & Thought Leadership | G4: =SUMIF($D$14:$D$57,$D4,$G$14:$G$57) -> 58
D5: Sales Enablement | G5: =SUMIF($D$14:$D$57,$D5,$G$14:$G$57) -> 30030
D6: Tools & Martech | G6: =SUMIF($D$14:$D$57,$D6,$G$14:$G$57) -> 24
D7: Agency / External | G7: =SUMIF($D$14:$D$57,$D7,$G$14:$G$57) -> 27
G8: =SUM(G2:G7) -> 30181
G11: =SUM(G13:G64) -> 30181
A12: Date | B12: Supplier | C12: Description/Campaign | D12: Category | E12: Budget Line | F12: Region | G12: Cost (£) | H12: Status | I12: Notes
A14: 01.01.26 | B14: linkedin | C14: Q1 Content Campaign | D14: Demand Generation | G14: 5
D15: Demand Generation | G15: 6
D16: Content & Thought Leadership | G16: 25
D17: Sales Enablement | G17: 30000
D18: Tools & Martech | G18: 8
D19: Agency / External | G19: 9
D20: Demand Generation | G20: 3
D21: Content & Thought Leadership | G21: 4
D22: Content & Thought Leadership | G22: 5
D23: Sales Enablement | G23: 6
D24: Brand & Awareness | G24: 5
D25: Demand Generation | G25: 6
D26: Content & Thought Leadership | G26: 3
... D43: Sales Enablement | G43: 6
